README.md
setup.py
PyHutool.egg-info/PKG-INFO
PyHutool.egg-info/SOURCES.txt
PyHutool.egg-info/dependency_links.txt
PyHutool.egg-info/requires.txt
PyHutool.egg-info/top_level.txt
pyhutool/Operator.py
pyhutool/QRCode.py
pyhutool/Verification.py
pyhutool/__init__.py